MANIFEST.in
README.md
setup.cfg
setup.py
pm20_5/.DS_Store
pm20_5/__init__.py
pm20_5/questions.py
pm20_5.egg-info/PKG-INFO
pm20_5.egg-info/SOURCES.txt
pm20_5.egg-info/dependency_links.txt
pm20_5.egg-info/requires.txt
pm20_5.egg-info/top_level.txt
pm20_5/qu1/.DS_Store
pm20_5/qu1/__init__.py
pm20_5/qu1/q1_10.png
pm20_5/qu1/q1_11.png
pm20_5/qu1/q1_12.png
pm20_5/qu1/q1_13.png
pm20_5/qu1/q1_14.png
pm20_5/qu1/q1_15.png
pm20_5/qu1/q1_16_1.png
pm20_5/qu1/q1_16_2.png
pm20_5/qu1/q1_17_1.png
pm20_5/qu1/q1_17_2.png
pm20_5/qu1/q1_18.png
pm20_5/qu1/q1_19.png
pm20_5/qu1/q1_1_1.png
pm20_5/qu1/q1_1_2.png
pm20_5/qu1/q1_2.png
pm20_5/qu1/q1_20.png
pm20_5/qu1/q1_21.png
pm20_5/qu1/q1_22.png
pm20_5/qu1/q1_23_1.png
pm20_5/qu1/q1_23_2.png
pm20_5/qu1/q1_24.png
pm20_5/qu1/q1_25.png
pm20_5/qu1/q1_26.png
pm20_5/qu1/q1_27.png
pm20_5/qu1/q1_28.png
pm20_5/qu1/q1_29.png
pm20_5/qu1/q1_3.png
pm20_5/qu1/q1_30.png
pm20_5/qu1/q1_31.png
pm20_5/qu1/q1_32.png
pm20_5/qu1/q1_33.png
pm20_5/qu1/q1_34.png
pm20_5/qu1/q1_35_1.png
pm20_5/qu1/q1_35_2.png
pm20_5/qu1/q1_36.png
pm20_5/qu1/q1_37.png
pm20_5/qu1/q1_38.png
pm20_5/qu1/q1_4.png
pm20_5/qu1/q1_5.png
pm20_5/qu1/q1_6.png
pm20_5/qu1/q1_7.png
pm20_5/qu1/q1_8.png
pm20_5/qu1/q1_9.png
pm20_5/qu1/q1_task1.png
pm20_5/qu1/q1_task2.png
pm20_5/qu2/__init__.py
pm20_5/qu2/q2_10_1.png
pm20_5/qu2/q2_10_2.png
pm20_5/qu2/q2_10_3.png
pm20_5/qu2/q2_11_1.png
pm20_5/qu2/q2_11_2.png
pm20_5/qu2/q2_12_1.png
pm20_5/qu2/q2_12_2.png
pm20_5/qu2/q2_13_1.png
pm20_5/qu2/q2_13_2.png
pm20_5/qu2/q2_14_1.png
pm20_5/qu2/q2_14_2.png
pm20_5/qu2/q2_15_1.png
pm20_5/qu2/q2_15_2.png
pm20_5/qu2/q2_16_1.png
pm20_5/qu2/q2_16_2.png
pm20_5/qu2/q2_17_1.png
pm20_5/qu2/q2_17_2.png
pm20_5/qu2/q2_18_1.png
pm20_5/qu2/q2_18_2.png
pm20_5/qu2/q2_19_1.png
pm20_5/qu2/q2_19_2.png
pm20_5/qu2/q2_1_1.png
pm20_5/qu2/q2_1_2.png
pm20_5/qu2/q2_20_1.png
pm20_5/qu2/q2_20_2.png
pm20_5/qu2/q2_21.png
pm20_5/qu2/q2_22.png
pm20_5/qu2/q2_23_1.png
pm20_5/qu2/q2_23_2.png
pm20_5/qu2/q2_24.png
pm20_5/qu2/q2_25.png
pm20_5/qu2/q2_26.png
pm20_5/qu2/q2_2_1.png
pm20_5/qu2/q2_2_2.png
pm20_5/qu2/q2_2_3.png
pm20_5/qu2/q2_3.png
pm20_5/qu2/q2_3_1.png
pm20_5/qu2/q2_3_2.png
pm20_5/qu2/q2_4.png
